{"spawn":{"pos":{"field_177962_a":0,"field_177960_b":65,"field_177961_c":0}},"RoZenKai":{"pos":{"field_177962_a":1991,"field_177960_b":2,"field_177961_c":1993}},"Photonik":{"pos":{"field_177962_a":-964,"field_177960_b":60,"field_177961_c":-1001}},"_Pilot_":{"pos":{"field_177962_a":-2000,"field_177960_b":60,"field_177961_c":2000}},"william0902":{"pos":{"field_177962_a":-1004,"field_177960_b":59,"field_177961_c":1001}},"TheGoCartRaider":{"pos":{"field_177962_a":1000,"field_177960_b":60,"field_177961_c":-1000}},"_Wooly":{"pos":{"field_177962_a":-2000,"field_177960_b":60,"field_177961_c":-2000}}}